cli/__init__.py
cli/dsf2flac/__init__.py
cli/dts2flac/__init__.py
cli/flac2wav/__init__.py
cli/mkv2flac/__init__.py
cli/surroundgen/__init__.py
cli/surroundsep/__init__.py
surroundgen-0.0.1.dist-info/LICENSE
surroundgen-0.0.1.dist-info/METADATA
surroundgen-0.0.1.dist-info/WHEEL
surroundgen-0.0.1.dist-info/entry_points.txt
surroundgen-0.0.1.dist-info/top_level.txt
surroundgen-0.0.1.dist-info/RECORD
