Metadata-Version: 2.1
Name: surroundgen
Version: 0.0.1
Summary: Surroundgen is a surround and immersive spatial audio toolkit. It helps you separate and generate multichannel audio files.
Home-page: https://surroundgen.dev
Author: Axel Delafosse
Author-email: axeldelafosse@gmail.com
License: MIT
Classifier: Programming Language :: Python :: 3
Classifier: License :: OSI Approved :: MIT License
Classifier: Operating System :: OS Independent
Requires-Python: >=3.9
License-File: LICENSE
